[
    {
        "id": 1,
        "name":"Arjun Kumar",
        "rollno":"1",
        "std": "lkg",
        "address":"Shirur-Pune",
        "img":"/assets/dummy.jpg"
    },
    {
        "id": 2,
        "name":"Arjun Kumar",
        "rollno":"1",
        "std": "lkg",
        "address":"Shirur-Pune",
        "img":"/assets/dummy.jpg"

    },
    {
       "id": 3,
        "name":"Arjun Kumar",
        "rollno":"1",
        "std": "lkg",
        "address":"Shirur-Pune",
        "img":"/assets/dummy.jpg"
    },
    {
        "id": 4,
        "name":"Arjun Kumar",
        "rollno":"1",
        "std": "lkg",
        "address":"Shirur-Pune",
        "img":"/assets/dummy.jpg"
    },
    {
        "id": 5,
        "name":"Arjun Kumar",
        "rollno":"1",
        "std": "lkg",
        "address":"Shirur-Pune",
        "img":"/assets/dummy.jpg"

    },
    {
        "id": 6,
        "name":"Arjun Kumar",
        "rollno":"1",
        "std": "lkg",
        "address":"Shirur-Pune",
        "img":"/assets/dummy.jpg"

    },
    {
        "id": 7,
        "name":"Arjun Kumar",
        "rollno":"1",
        "std": "lkg",
        "address":"Shirur-Pune",
        "img":"/assets/dummy.jpg"
    },
    {
       "id": 8,
        "name":"Arjun Kumar",
        "rollno":"1",
        "std": "lkg",
        "address":"Shirur-Pune",
        "img":"/assets/dummy.jpg"

    },
    {
        "id": 9,
        "name":"Arjun Kumar",
        "rollno":"1",
        "std": "lkg",
        "address":"Shirur-Pune",
        "img":"/assets/dummy.jpg"
    },
    {
        "id": 10,
        "name":"Arjun Kumar",
        "rollno":"1",
        "std": "lkg",
        "address":"Shirur-Pune",
        "img":"/assets/dummy.jpg"
    }
]